OasisPy/MR.py
OasisPy/__init__.py
OasisPy/align.py
OasisPy/align_astroalign.py
OasisPy/authorization.py
OasisPy/background.py
OasisPy/bad_rejection.py
OasisPy/check_saturation.py
OasisPy/combine.py
OasisPy/combine_swarp.py
OasisPy/data_request.py
OasisPy/extract.py
OasisPy/filters.py
OasisPy/get.py
OasisPy/initialize.py
OasisPy/intensity_match.py
OasisPy/make_stars.py
OasisPy/mask.py
OasisPy/montage.py
OasisPy/obtain.py
OasisPy/optimize.py
OasisPy/pipeline.py
OasisPy/poisson_fit.py
OasisPy/proposals.py
OasisPy/psf.py
OasisPy/ref_image.py
OasisPy/run.py
OasisPy/sex.py
OasisPy/simulation.py
OasisPy/subtract.py
OasisPy/subtract_ais.py
OasisPy/subtract_hotpants.py
OasisPy/test.py
OasisPy/AIS/package/install.csh
OasisPy/AIS/package/short.h
OasisPy/AIS/package/Bphot/Bphot
OasisPy/AIS/package/Bphot/aperphot.c
OasisPy/AIS/package/Bphot/aperphot.o
OasisPy/AIS/package/Bphot/background.c
OasisPy/AIS/package/Bphot/background.o
OasisPy/AIS/package/Bphot/cent.c
OasisPy/AIS/package/Bphot/cent.o
OasisPy/AIS/package/Bphot/default_config
OasisPy/AIS/package/Bphot/main.c
OasisPy/AIS/package/Bphot/main.o
OasisPy/AIS/package/Bphot/make_psf.c
OasisPy/AIS/package/Bphot/make_psf.o
OasisPy/AIS/package/Bphot/makefile
OasisPy/AIS/package/Bphot/max.c
OasisPy/AIS/package/Bphot/max.o
OasisPy/AIS/package/Bphot/quick_sort.c
OasisPy/AIS/package/Bphot/quick_sort.o
OasisPy/AIS/package/Bphot/read_config.c
OasisPy/AIS/package/Bphot/read_config.o
OasisPy/AIS/package/Bphot/read_header.c
OasisPy/AIS/package/Bphot/read_header.c~
OasisPy/AIS/package/Bphot/read_header.o
OasisPy/AIS/package/Bphot/read_image.c
OasisPy/AIS/package/Bphot/read_image.c~
OasisPy/AIS/package/Bphot/read_image.o
OasisPy/AIS/package/Bphot/short.h
OasisPy/AIS/package/Bphot/splie2.c
OasisPy/AIS/package/Bphot/splie2.o
OasisPy/AIS/package/Bphot/spline.c
OasisPy/AIS/package/Bphot/spline.o
OasisPy/AIS/package/Bphot/spline2.c
OasisPy/AIS/package/Bphot/spline2.o
OasisPy/AIS/package/Bphot/splint.c
OasisPy/AIS/package/Bphot/splint.o
OasisPy-1.0.6.dist-info/LICENSE
OasisPy-1.0.6.dist-info/METADATA
OasisPy-1.0.6.dist-info/WHEEL
OasisPy-1.0.6.dist-info/entry_points.txt
OasisPy-1.0.6.dist-info/top_level.txt
OasisPy-1.0.6.dist-info/RECORD
